datafluent/__init__.py
datafluent-0.0.36.data/scripts/datafluent
datafluent-0.0.36.dist-info/LICENSE
datafluent-0.0.36.dist-info/METADATA
datafluent-0.0.36.dist-info/WHEEL
datafluent-0.0.36.dist-info/top_level.txt
datafluent-0.0.36.dist-info/RECORD
