Metadata-Version: 2.1
Name: datafluent
Version: 0.0.36
Summary: Build a better understanding of your data in PostgreSQL.
Home-page: https://github.com/marklit/datafluent_pg
Author: Mark Litwintschik
Author-email: mark@marksblogg.com
License: MIT
Project-URL: Bug Tracker, https://github.com/marklit/datafluent_pg/issues
Project-URL: Documentation, https://datafluent.readthedocs.io/en/latest/
Project-URL: Source Code, https://github.com/marklit/datafluent_pg
Platform: UNKNOWN
Classifier: Development Status :: 3 - Alpha
Classifier: Environment :: Console
Classifier: Intended Audience :: Developers
Classifier: Intended Audience :: System Administrators
Classifier: License :: OSI Approved :: MIT License
Classifier: Operating System :: POSIX :: Linux
Classifier: Programming Language :: Python :: 3.6
Classifier: Programming Language :: Python :: 3.7
Classifier: Programming Language :: Python :: 3.8
Classifier: Programming Language :: Python :: 3.9
Classifier: Topic :: Scientific/Engineering :: Information Analysis
License-File: LICENSE
Requires-Dist: humanfriendly
Requires-Dist: Pandas
Requires-Dist: psycopg2-binary
Requires-Dist: SQLAlchemy
Requires-Dist: typer
Requires-Dist: xlsxwriter
